triehard/__init__.py
triehard/cli.py
triehard-0.1.9.dist-info/entry_points.txt
triehard-0.1.9.dist-info/WHEEL
triehard-0.1.9.dist-info/METADATA
triehard-0.1.9.dist-info/RECORD
