Metadata-Version: 2.1
Name: triehard
Version: 0.1.9
Summary: A badly implemented trie
License: MIT
Author: iCalculated
Author-email: fufa0001@gmail.com
Requires-Python: >=3.8,<4.0
Classifier: License :: OSI Approved :: MIT License
Classifier: Programming Language :: Python :: 3
Classifier: Programming Language :: Python :: 3.8
Classifier: Programming Language :: Python :: 3.9
Requires-Dist: python-nubia (>=0.2b5,<0.3)
Requires-Dist: requests (>=2.25.1,<3.0.0)
Requires-Dist: termcolor (>=1.1.0,<2.0.0)
